ess/isissans/__init__.py
ess/isissans/data.py
ess/isissans/general.py
ess/isissans/io.py
ess/isissans/mantidio.py
ess/isissans/sans2d.py
ess/isissans/visualization.py
ess/isissans/zoom.py
ess/loki/__init__.py
ess/loki/data.py
ess/loki/diagnostics.py
ess/loki/live.py
ess/loki/workflow.py
ess/sans/__init__.py
ess/sans/beam_center_finder.py
ess/sans/common.py
ess/sans/conversions.py
ess/sans/direct_beam.py
ess/sans/i_of_q.py
ess/sans/io.py
ess/sans/logging.py
ess/sans/masking.py
ess/sans/normalization.py
ess/sans/parameters.py
ess/sans/py.typed
ess/sans/types.py
ess/sans/workflow.py
esssans-26.1.1.dist-info/licenses/LICENSE
esssans-26.1.1.dist-info/METADATA
esssans-26.1.1.dist-info/WHEEL
esssans-26.1.1.dist-info/entry_points.txt
esssans-26.1.1.dist-info/top_level.txt
esssans-26.1.1.dist-info/RECORD
