Metadata-Version: 2.4
Name: esssans
Version: 26.1.1
Summary: SANS data reduction for the European Spallation Source
Author: Scipp contributors
License-Expression: BSD-3-Clause
Project-URL: Bug Tracker, https://github.com/scipp/esssans/issues
Project-URL: Documentation, https://scipp.github.io/esssans
Project-URL: Source, https://github.com/scipp/esssans
Classifier: Intended Audience :: Science/Research
Classifier: Natural Language :: English
Classifier: Operating System :: OS Independent
Classifier: Programming Language :: Python :: 3
Classifier: Programming Language :: Python :: 3 :: Only
Classifier: Programming Language :: Python :: 3.11
Classifier: Programming Language :: Python :: 3.12
Classifier: Programming Language :: Python :: 3.13
Classifier: Topic :: Scientific/Engineering
Classifier: Typing :: Typed
Requires-Python: >=3.11
License-File: LICENSE
Requires-Dist: dask>=2022.1.0
Requires-Dist: graphviz>=0.20
Requires-Dist: essreduce>=26.01.0
Requires-Dist: numpy>=1.26.4
Requires-Dist: pandas>=2.1.2
Requires-Dist: plopp>=25.03.0
Requires-Dist: pythreejs>=2.4.1
Requires-Dist: sciline>=25.08.0
Requires-Dist: scipp>=24.09.1
Requires-Dist: scippneutron>=25.02.1
Requires-Dist: scippnexus>=23.12.1
Provides-Extra: test
Requires-Dist: ipympl>=0.9.4; extra == "test"
Requires-Dist: pytest>=7.0; extra == "test"
Requires-Dist: pooch>=1.5; extra == "test"
Requires-Dist: scipy>=1.15.0; extra == "test"
Dynamic: license-file
